{
  "id": 1,
  "name": "Mind game :) - Addition quiz",
  "TestDuration" :  100,
  "description": "********************Question of type a+b**************",
  "questions": [
    {
      "id": 1000,
      "name": "what will be the output of 58+5",
      "options": [
        {
          "id": 2000,
          "questionId": 1000,
          "name": "64",
          "isAnswer": false
        },
        {
          "id": 2001,
          "questionId": 1000,
          "name": "63",
          "isAnswer": true
        },
        {
          "id": 2002,
          "questionId": 1000,
          "name": "65",
          "isAnswer": false
        },
        {
          "id": 2003,
          "questionId": 1000,
          "name": "None of the above",
          "isAnswer": false
        }
      ]
    },
    {
      "id": 1001,
      "name": "what will be the output of 58+0",
      "options": [
        {
          "id": 2004,
          "questionId": 1001,
          "name": "59",
          "isAnswer": false
        },
        {
          "id": 2005,
          "questionId": 1001,
          "name": "65",
          "isAnswer": false
        },
        {
          "id": 2006,
          "questionId": 1001,
          "name": "63",
          "isAnswer": false
        },
        {
          "id": 2007,
          "questionId": 1001,
          "name": "None of the above",
          "isAnswer": true
        }
      ]
    },
    {
      "id": 1002,
      "name": "what will be the output of 69+61",
      "options": [
        {
          "id": 2008,
          "questionId": 1002,
          "name": "130",
          "isAnswer": true
        },
        {
          "id": 2009,
          "questionId": 1002,
          "name": "131",
          "isAnswer": false
        },
        {
          "id": 2010,
          "questionId": 1002,
          "name": "113",
          "isAnswer": false
        },
        {
          "id": 2011,
          "questionId": 1002,
          "name": "103",
          "isAnswer": false
        }
      ]
    },
    {
      "id": 1003,
      "name": "what will be the output of -5+5",
      "options": [
        {
          "id": 2012,
          "questionId": 1003,
          "name": "0",
          "isAnswer": true
        },
        {
          "id": 2013,
          "questionId": 1003,
          "name": "10",
          "isAnswer": true
        },
        {
          "id": 2014,
          "questionId": 1003,
          "name": "-10",
          "isAnswer": false
        },
        {
          "id": 2015,
          "questionId": 1003,
          "name": "None of the above",
          "isAnswer": false
        }
      ]
    },
    {
      "id": 1004,
      "name": "what will be the output of -120+110",
      "options": [
        {
          "id": 2016,
          "questionId": 1004,
          "name": "-10",
          "isAnswer": true
        },
        {
          "id": 2017,
          "questionId": 1004,
          "name": "-100",
          "isAnswer": false
        },
        {
          "id": 2018,
          "questionId": 1004,
          "name": "01",
          "isAnswer": false
        },
        {
          "id": 2019,
          "questionId": 1004,
          "name": "None of the above",
          "isAnswer": false
        }
      ]
    },
    {
      "id": 1005,
      "name": "what will be the output of -6+5",
      "options": [
        {
          "id": 2020,
          "questionId": 1005,
          "name": "1",
          "isAnswer": false
        },
        {
          "id": 2021,
          "questionId": 1005,
          "name": "11",
          "isAnswer": false
        },
        {
          "id": 2022,
          "questionId": 1005,
          "name": "-1",
          "isAnswer": true
        },
        {
          "id": 2024,
          "questionId": 1005,
          "name": "None of the above",
          "isAnswer": false
        }
      ]
    },
    {
      "id": 1008,
      "name": "what will be the output of 162+197",
      "options": [
        {
          "id": 2025,
          "questionId": 1008,
          "name": "395",
          "isAnswer": false
        },
        {
          "id": 2026,
          "questionId": 1008,
          "name": "359",
          "isAnswer": true
        },
        {
          "id": 2027,
          "questionId": 1008,
          "name": "369",
          "isAnswer": true
        },
        {
          "id": 2028,
          "questionId": 1008,
          "name": "349",
          "isAnswer": false
        }
      ]
    },
    {
      "id": 1009,
      "name": "what will be the output of 157+168",
      "options": [
        {
          "id": 2029,
          "questionId": 1009,
          "name": "3251",
          "isAnswer": false
        },
        {
          "id": 20020,
          "questionId": 1009,
          "name": "65",
          "isAnswer": false
        },
        {
          "id": 2021,
          "questionId": 1009,
          "name": "630",
          "isAnswer": false
        },
        {
          "id": 2022,
          "questionId": 1009,
          "name": "325",
          "isAnswer": true
        }
      ]
    },
    {
      "id": 1010,
      "name": "what will be the output of 658+981",
      "options": [
        {
          "id": 2023,
          "questionId": 1010,
          "name": "1693",
          "isAnswer": false
        },
        {
          "id": 2024,
          "questionId": 1010,
          "name": "1639",
          "isAnswer": false
        },
        {
          "id": 2025,
          "questionId": 1010,
          "name": "1639",
          "isAnswer": true
        },
        {
          "id": 2026,
          "questionId": 1010,
          "name": "None of the above",
          "isAnswer": false
        }
      ]
    },
    {
      "id": 1011,
      "name": "what will be the output of 624+549",
      "options": [
        {
          "id": 2027,
          "questionId": 1011,
          "name": "1100",
          "isAnswer": false
        },
        {
          "id": 2028,
          "questionId": 1011,
          "name": "1137",
          "isAnswer": false
        },
        {
          "id": 2029,
          "questionId": 1011,
          "name": "1173",
          "isAnswer": true
        },
        {
          "id": 2030,
          "questionId": 1011,
          "name": "1139",
          "isAnswer": false
        }
      ]
    },
    {
      "id": 1012,
      "name": "what will be the output of 1147+1159",
      "options": [
        {
          "id": 2031,
          "questionId": 1012,
          "name": "2300",
          "isAnswer": false
        },
        {
          "id": 2032,
          "questionId": 1012,
          "name": "2451",
          "isAnswer": false
        },
        {
          "id": 2033,
          "questionId": 1012,
          "name": "2306",
          "isAnswer": true
        },
        {
          "id": 2034,
          "questionId": 1012,
          "name": "2360",
          "isAnswer": false
        }
      ]
    },
    {
      "id": 1013,
      "name": "what will be the output of 2489+2984",
      "options": [
        {
          "id": 2035,
          "questionId": 1013,
          "name": "5473",
          "isAnswer": true
        },
        {
          "id": 2036,
          "questionId": 1013,
          "name": "1137",
          "isAnswer": false
        },
        {
          "id": 2037,
          "questionId": 1013,
          "name": "1173",
          "isAnswer": false
        },
        {
          "id": 2038,
          "questionId": 1013,
          "name": "2306",
          "isAnswer": false
        }
      ]
    },
    {
      "id": 1014,
      "name": "what will be the output of 11797+11879",
      "options": [
        {
          "id": 2039,
          "questionId": 1014,
          "name": "15100",
          "isAnswer": false
        },
        {
          "id": 2040,
          "questionId": 1014,
          "name": "23676",
          "isAnswer": true
        },
        {
          "id": 2029,
          "questionId": 1014,
          "name": "12173",
          "isAnswer": false
        },
        {
          "id": 2030,
          "questionId": 1014,
          "name": "35139",
          "isAnswer": false
        }
      ]
    },
    {
      "id": 1015,
      "name": "what will be the output of 264798+1456",
      "options": [
        {
          "id": 2031,
          "questionId": 1015,
          "name": "266254",
          "isAnswer": true
        },
        {
          "id": 2032,
          "questionId": 1014,
          "name": "266245",
          "isAnswer": false
        },
        {
          "id": 2033,
          "questionId": 1014,
          "name": "266250",
          "isAnswer": false
        },
        {
          "id": 2034,
          "questionId": 1014,
          "name": "266215",
          "isAnswer": false
        }
      ]
    },
    {
      "id": 1016,
      "name": "what will be the output of 65478971+64781",
      "options": [
        {
          "id": 2031,
          "questionId": 1016,
          "name": "65446568",
          "isAnswer": false
        },
        {
          "id": 2032,
          "questionId": 1016,
          "name": "789641345",
          "isAnswer": false
        },
        {
          "id": 2033,
          "questionId": 1016,
          "name": "65543752",
          "isAnswer": true
        },
        {
          "id": 2034,
          "questionId": 1016,
          "name": "662514791",
          "isAnswer": false
        }
      ]
    }
  ]
}